mseep_utcp-0.1.3.dist-info/licenses/LICENSE
tests/__init__.py
tests/client/__init__.py
tests/client/test_openapi_converter.py
tests/client/test_openapi_converter_auth.py
tests/client/transport_interfaces/__init__.py
tests/client/transport_interfaces/mock_http_mcp_server.py
tests/client/transport_interfaces/mock_mcp_server.py
tests/client/transport_interfaces/test_cli_transport.py
tests/client/transport_interfaces/test_graphql_transport.py
tests/client/transport_interfaces/test_http_transport.py
tests/client/transport_interfaces/test_mcp_http_transport.py
tests/client/transport_interfaces/test_mcp_transport.py
tests/client/transport_interfaces/test_sse_transport.py
tests/client/transport_interfaces/test_streamable_http_transport.py
tests/client/transport_interfaces/test_text_transport.py
mseep_utcp-0.1.3.dist-info/METADATA
mseep_utcp-0.1.3.dist-info/WHEEL
mseep_utcp-0.1.3.dist-info/top_level.txt
mseep_utcp-0.1.3.dist-info/RECORD
