Metadata-Version: 2.4
Name: mseep-utcp
Version: 0.1.3
Summary: Universal Tool Calling Protocol (UTCP) client library for Python
Home-page: https://github.com/mseep
Author: mseep
Author-email: support@skydeck.ai
Maintainer: mseep
Maintainer-email: support@skydeck.ai
Keywords: mseep
Classifier: Programming Language :: Python :: 3
Classifier: License :: OSI Approved :: MIT License
Classifier: Operating System :: OS Independent
Requires-Python: >=3.6
License-File: LICENSE
Requires-Dist: pydantic>=2.0
Requires-Dist: authlib>=1.0
Requires-Dist: python-dotenv>=1.0
Requires-Dist: tomli>=2.0
Requires-Dist: aiohttp>=3.8
Requires-Dist: mcp>=1.0
Requires-Dist: pyyaml>=6.0
Dynamic: author
Dynamic: author-email
Dynamic: classifier
Dynamic: description
Dynamic: description-content-type
Dynamic: home-page
Dynamic: keywords
Dynamic: license-file
Dynamic: maintainer
Dynamic: maintainer-email
Dynamic: requires-dist
Dynamic: requires-python
Dynamic: summary
